<annotation>
  <folder>dout</folder>
  <filename>216</filename>
  <path>/home/liuyao/Documents/Yolo_sample/20170327/infrared/images/dout/216.xml</path>
  <source>
    <database>Unknown</database>
  </source>
  <size>
    <width>406</width>
    <height>309</height>
    <depth>3</depth>
  </size>
  <segmented>0</segmented>
  <object>
    <name>line</name>
    <pose>Unspecified</pose>
    <truncated>0</truncated>
    <difficult>0</difficult>
    <bndbox>
      <xmin>108</xmin>
      <ymin>144</ymin>
      <xmax>141</xmax>
      <ymax>206</ymax>
    </bndbox>
  </object>
  <object>
    <name>line</name>
    <pose>Unspecified</pose>
    <truncated>0</truncated>
    <difficult>0</difficult>
    <bndbox>
      <xmin>272</xmin>
      <ymin>122</ymin>
      <xmax>298</xmax>
      <ymax>158</ymax>
    </bndbox>
  </object>
</annotation>