<annotation>
  <folder>dout</folder>
  <filename>233</filename>
  <path>/home/liuyao/Documents/Yolo_sample/20170327/infrared/images/dout/233.xml</path>
  <source>
    <database>Unknown</database>
  </source>
  <size>
    <width>406</width>
    <height>309</height>
    <depth>3</depth>
  </size>
  <segmented>0</segmented>
  <object>
    <name>line</name>
    <pose>Unspecified</pose>
    <truncated>0</truncated>
    <difficult>0</difficult>
    <bndbox>
      <xmin>108</xmin>
      <ymin>133</ymin>
      <xmax>135</xmax>
      <ymax>199</ymax>
    </bndbox>
  </object>
  <object>
    <name>line</name>
    <pose>Unspecified</pose>
    <truncated>0</truncated>
    <difficult>0</difficult>
    <bndbox>
      <xmin>275</xmin>
      <ymin>132</ymin>
      <xmax>296</xmax>
      <ymax>169</ymax>
    </bndbox>
  </object>
</annotation>